{
  "_format": "hh-sol-cache-2",
  "files": {
    "/workspaces/CoffeeCraze/contracts/contracts/DAOContract.sol": {
      "lastModificationDate": 1751809683694,
      "contentHash": "cc44359dccc37b401c4135cd2e0496ad",
      "sourceName": "contracts/DAOContract.sol",
      "solcConfig": {
        "version": "0.8.24",
        "settings": {
          "evmVersion": "paris",
          "optimizer": {
            "enabled": false,
            "runs": 200
          },
          "outputSelection": {
            "*": {
              "*": [
                "abi",
                "evm.bytecode",
                "evm.deployedBytecode",
                "evm.methodIdentifiers",
                "metadata",
                "storageLayout"
              ],
              "": [
                "ast"
              ]
            }
          }
        }
      },
      "imports": [
        "@openzeppelin/contracts/access/Ownable.sol"
      ],
      "versionPragmas": [
        "^0.8.24"
      ],
      "artifacts": [
        "DAOContract"
      ]
    },
    "/workspaces/CoffeeCraze/node_modules/@openzeppelin/contracts/access/Ownable.sol": {
      "lastModificationDate": 1751804741880,
      "contentHash": "d3c790edc9ccf808a17c5a6cd13614fd",
      "sourceName": "@openzeppelin/contracts/access/Ownable.sol",
      "solcConfig": {
        "version": "0.8.24",
        "settings": {
          "evmVersion": "paris",
          "optimizer": {
            "enabled": false,
            "runs": 200
          },
          "outputSelection": {
            "*": {
              "*": [
                "abi",
                "evm.bytecode",
                "evm.deployedBytecode",
                "evm.methodIdentifiers",
                "metadata",
                "storageLayout"
              ],
              "": [
                "ast"
              ]
            }
          }
        }
      },
      "imports": [
        "../utils/Context.sol"
      ],
      "versionPragmas": [
        "^0.8.20"
      ],
      "artifacts": [
        "Ownable"
      ]
    },
    "/workspaces/CoffeeCraze/node_modules/@openzeppelin/contracts/utils/Context.sol": {
      "lastModificationDate": 1751804741690,
      "contentHash": "67bfbc07588eb8683b3fd8f6f909563e",
      "sourceName": "@openzeppelin/contracts/utils/Context.sol",
      "solcConfig": {
        "version": "0.8.24",
        "settings": {
          "evmVersion": "paris",
          "optimizer": {
            "enabled": false,
            "runs": 200
          },
          "outputSelection": {
            "*": {
              "*": [
                "abi",
                "evm.bytecode",
                "evm.deployedBytecode",
                "evm.methodIdentifiers",
                "metadata",
                "storageLayout"
              ],
              "": [
                "ast"
              ]
            }
          }
        }
      },
      "imports": [],
      "versionPragmas": [
        "^0.8.20"
      ],
      "artifacts": [
        "Context"
      ]
    },
    "/workspaces/CoffeeCraze/node_modules/@openzeppelin/contracts/token/ERC721/ERC721.sol": {
      "lastModificationDate": 1751804741712,
      "contentHash": "a7951c81f7037d558c6d2f220b0cb38e",
      "sourceName": "@openzeppelin/contracts/token/ERC721/ERC721.sol",
      "solcConfig": {
        "version": "0.8.24",
        "settings": {
          "evmVersion": "paris",
          "optimizer": {
            "enabled": false,
            "runs": 200
          },
          "outputSelection": {
            "*": {
              "*": [
                "abi",
                "evm.bytecode",
                "evm.deployedBytecode",
                "evm.methodIdentifiers",
                "metadata",
                "storageLayout"
              ],
              "": [
                "ast"
              ]
            }
          }
        }
      },
      "imports": [
        "./IERC721.sol",
        "./extensions/IERC721Metadata.sol",
        "./utils/ERC721Utils.sol",
        "../../utils/Context.sol",
        "../../utils/Strings.sol",
        "../../utils/introspection/ERC165.sol",
        "../../interfaces/draft-IERC6093.sol"
      ],
      "versionPragmas": [
        "^0.8.20"
      ],
      "artifacts": [
        "ERC721"
      ]
    },
    "/workspaces/CoffeeCraze/node_modules/@openzeppelin/contracts/utils/Strings.sol": {
      "lastModificationDate": 1751804741894,
      "contentHash": "13dbc135f563c72a11b1cf4fbb5fb284",
      "sourceName": "@openzeppelin/contracts/utils/Strings.sol",
      "solcConfig": {
        "version": "0.8.24",
        "settings": {
          "evmVersion": "paris",
          "optimizer": {
            "enabled": false,
            "runs": 200
          },
          "outputSelection": {
            "*": {
              "*": [
                "abi",
                "evm.bytecode",
                "evm.deployedBytecode",
                "evm.methodIdentifiers",
                "metadata",
                "storageLayout"
              ],
              "": [
                "ast"
              ]
            }
          }
        }
      },
      "imports": [
        "./math/Math.sol",
        "./math/SafeCast.sol",
        "./math/SignedMath.sol"
      ],
      "versionPragmas": [
        "^0.8.20"
      ],
      "artifacts": [
        "Strings"
      ]
    },
    "/workspaces/CoffeeCraze/node_modules/@openzeppelin/contracts/interfaces/draft-IERC6093.sol": {
      "lastModificationDate": 1751804741694,
      "contentHash": "267d92fe4de67b1bdb3302c08f387dbf",
      "sourceName": "@openzeppelin/contracts/interfaces/draft-IERC6093.sol",
      "solcConfig": {
        "version": "0.8.24",
        "settings": {
          "evmVersion": "paris",
          "optimizer": {
            "enabled": false,
            "runs": 200
          },
          "outputSelection": {
            "*": {
              "*": [
                "abi",
                "evm.bytecode",
                "evm.deployedBytecode",
                "evm.methodIdentifiers",
                "metadata",
                "storageLayout"
              ],
              "": [
                "ast"
              ]
            }
          }
        }
      },
      "imports": [],
      "versionPragmas": [
        "^0.8.20"
      ],
      "artifacts": [
        "IERC1155Errors",
        "IERC20Errors",
        "IERC721Errors"
      ]
    },
    "/workspaces/CoffeeCraze/node_modules/@openzeppelin/contracts/utils/introspection/ERC165.sol": {
      "lastModificationDate": 1751804741703,
      "contentHash": "7c03c1e37c3dc24eafb76dc2b8a5c3a6",
      "sourceName": "@openzeppelin/contracts/utils/introspection/ERC165.sol",
      "solcConfig": {
        "version": "0.8.24",
        "settings": {
          "evmVersion": "paris",
          "optimizer": {
            "enabled": false,
            "runs": 200
          },
          "outputSelection": {
            "*": {
              "*": [
                "abi",
                "evm.bytecode",
                "evm.deployedBytecode",
                "evm.methodIdentifiers",
                "metadata",
                "storageLayout"
              ],
              "": [
                "ast"
              ]
            }
          }
        }
      },
      "imports": [
        "./IERC165.sol"
      ],
      "versionPragmas": [
        "^0.8.20"
      ],
      "artifacts": [
        "ERC165"
      ]
    },
    "/workspaces/CoffeeCraze/node_modules/@openzeppelin/contracts/token/ERC721/IERC721.sol": {
      "lastModificationDate": 1751804741836,
      "contentHash": "1fdc621cd6747e8985e11fc76ce74511",
      "sourceName": "@openzeppelin/contracts/token/ERC721/IERC721.sol",
      "solcConfig": {
        "version": "0.8.24",
        "settings": {
          "evmVersion": "paris",
          "optimizer": {
            "enabled": false,
            "runs": 200
          },
          "outputSelection": {
            "*": {
              "*": [
                "abi",
                "evm.bytecode",
                "evm.deployedBytecode",
                "evm.methodIdentifiers",
                "metadata",
                "storageLayout"
              ],
              "": [
                "ast"
              ]
            }
          }
        }
      },
      "imports": [
        "../../utils/introspection/IERC165.sol"
      ],
      "versionPragmas": [
        "^0.8.20"
      ],
      "artifacts": [
        "IERC721"
      ]
    },
    "/workspaces/CoffeeCraze/node_modules/@openzeppelin/contracts/token/ERC721/extensions/IERC721Metadata.sol": {
      "lastModificationDate": 1751804741838,
      "contentHash": "12c206f185cb951213799561fdcaa40d",
      "sourceName": "@openzeppelin/contracts/token/ERC721/extensions/IERC721Metadata.sol",
      "solcConfig": {
        "version": "0.8.24",
        "settings": {
          "evmVersion": "paris",
          "optimizer": {
            "enabled": false,
            "runs": 200
          },
          "outputSelection": {
            "*": {
              "*": [
                "abi",
                "evm.bytecode",
                "evm.deployedBytecode",
                "evm.methodIdentifiers",
                "metadata",
                "storageLayout"
              ],
              "": [
                "ast"
              ]
            }
          }
        }
      },
      "imports": [
        "../IERC721.sol"
      ],
      "versionPragmas": [
        "^0.8.20"
      ],
      "artifacts": [
        "IERC721Metadata"
      ]
    },
    "/workspaces/CoffeeCraze/node_modules/@openzeppelin/contracts/token/ERC721/utils/ERC721Utils.sol": {
      "lastModificationDate": 1751804741715,
      "contentHash": "e12814872b31b0af06106796a6621b04",
      "sourceName": "@openzeppelin/contracts/token/ERC721/utils/ERC721Utils.sol",
      "solcConfig": {
        "version": "0.8.24",
        "settings": {
          "evmVersion": "paris",
          "optimizer": {
            "enabled": false,
            "runs": 200
          },
          "outputSelection": {
            "*": {
              "*": [
                "abi",
                "evm.bytecode",
                "evm.deployedBytecode",
                "evm.methodIdentifiers",
                "metadata",
                "storageLayout"
              ],
              "": [
                "ast"
              ]
            }
          }
        }
      },
      "imports": [
        "../IERC721Receiver.sol",
        "../../../interfaces/draft-IERC6093.sol"
      ],
      "versionPragmas": [
        "^0.8.20"
      ],
      "artifacts": [
        "ERC721Utils"
      ]
    },
    "/workspaces/CoffeeCraze/node_modules/@openzeppelin/contracts/utils/math/Math.sol": {
      "lastModificationDate": 1751804741868,
      "contentHash": "5ec781e33d3a9ac91ffdc83d94420412",
      "sourceName": "@openzeppelin/contracts/utils/math/Math.sol",
      "solcConfig": {
        "version": "0.8.24",
        "settings": {
          "evmVersion": "paris",
          "optimizer": {
            "enabled": false,
            "runs": 200
          },
          "outputSelection": {
            "*": {
              "*": [
                "abi",
                "evm.bytecode",
                "evm.deployedBytecode",
                "evm.methodIdentifiers",
                "metadata",
                "storageLayout"
              ],
              "": [
                "ast"
              ]
            }
          }
        }
      },
      "imports": [
        "../Panic.sol",
        "./SafeCast.sol"
      ],
      "versionPragmas": [
        "^0.8.20"
      ],
      "artifacts": [
        "Math"
      ]
    },
    "/workspaces/CoffeeCraze/node_modules/@openzeppelin/contracts/utils/math/SafeCast.sol": {
      "lastModificationDate": 1751804741892,
      "contentHash": "2adca1150f58fc6f3d1f0a0f22ee7cca",
      "sourceName": "@openzeppelin/contracts/utils/math/SafeCast.sol",
      "solcConfig": {
        "version": "0.8.24",
        "settings": {
          "evmVersion": "paris",
          "optimizer": {
            "enabled": false,
            "runs": 200
          },
          "outputSelection": {
            "*": {
              "*": [
                "abi",
                "evm.bytecode",
                "evm.deployedBytecode",
                "evm.methodIdentifiers",
                "metadata",
                "storageLayout"
              ],
              "": [
                "ast"
              ]
            }
          }
        }
      },
      "imports": [],
      "versionPragmas": [
        "^0.8.20"
      ],
      "artifacts": [
        "SafeCast"
      ]
    },
    "/workspaces/CoffeeCraze/node_modules/@openzeppelin/contracts/utils/math/SignedMath.sol": {
      "lastModificationDate": 1751804741893,
      "contentHash": "ae3528afb8bdb0a7dcfba5b115ee8074",
      "sourceName": "@openzeppelin/contracts/utils/math/SignedMath.sol",
      "solcConfig": {
        "version": "0.8.24",
        "settings": {
          "evmVersion": "paris",
          "optimizer": {
            "enabled": false,
            "runs": 200
          },
          "outputSelection": {
            "*": {
              "*": [
                "abi",
                "evm.bytecode",
                "evm.deployedBytecode",
                "evm.methodIdentifiers",
                "metadata",
                "storageLayout"
              ],
              "": [
                "ast"
              ]
            }
          }
        }
      },
      "imports": [
        "./SafeCast.sol"
      ],
      "versionPragmas": [
        "^0.8.20"
      ],
      "artifacts": [
        "SignedMath"
      ]
    },
    "/workspaces/CoffeeCraze/node_modules/@openzeppelin/contracts/utils/Panic.sol": {
      "lastModificationDate": 1751804741883,
      "contentHash": "2133dc13536b4a6a98131e431fac59e1",
      "sourceName": "@openzeppelin/contracts/utils/Panic.sol",
      "solcConfig": {
        "version": "0.8.24",
        "settings": {
          "evmVersion": "paris",
          "optimizer": {
            "enabled": false,
            "runs": 200
          },
          "outputSelection": {
            "*": {
              "*": [
                "abi",
                "evm.bytecode",
                "evm.deployedBytecode",
                "evm.methodIdentifiers",
                "metadata",
                "storageLayout"
              ],
              "": [
                "ast"
              ]
            }
          }
        }
      },
      "imports": [],
      "versionPragmas": [
        "^0.8.20"
      ],
      "artifacts": [
        "Panic"
      ]
    },
    "/workspaces/CoffeeCraze/node_modules/@openzeppelin/contracts/utils/introspection/IERC165.sol": {
      "lastModificationDate": 1751804741763,
      "contentHash": "bf0119eb2a570f219729ff38b6cd1df8",
      "sourceName": "@openzeppelin/contracts/utils/introspection/IERC165.sol",
      "solcConfig": {
        "version": "0.8.24",
        "settings": {
          "evmVersion": "paris",
          "optimizer": {
            "enabled": false,
            "runs": 200
          },
          "outputSelection": {
            "*": {
              "*": [
                "abi",
                "evm.bytecode",
                "evm.deployedBytecode",
                "evm.methodIdentifiers",
                "metadata",
                "storageLayout"
              ],
              "": [
                "ast"
              ]
            }
          }
        }
      },
      "imports": [],
      "versionPragmas": [
        "^0.8.20"
      ],
      "artifacts": [
        "IERC165"
      ]
    },
    "/workspaces/CoffeeCraze/node_modules/@openzeppelin/contracts/token/ERC721/IERC721Receiver.sol": {
      "lastModificationDate": 1751804741840,
      "contentHash": "729ce0904eb533489ffcc3bfe91237d4",
      "sourceName": "@openzeppelin/contracts/token/ERC721/IERC721Receiver.sol",
      "solcConfig": {
        "version": "0.8.24",
        "settings": {
          "evmVersion": "paris",
          "optimizer": {
            "enabled": false,
            "runs": 200
          },
          "outputSelection": {
            "*": {
              "*": [
                "abi",
                "evm.bytecode",
                "evm.deployedBytecode",
                "evm.methodIdentifiers",
                "metadata",
                "storageLayout"
              ],
              "": [
                "ast"
              ]
            }
          }
        }
      },
      "imports": [],
      "versionPragmas": [
        "^0.8.20"
      ],
      "artifacts": [
        "IERC721Receiver"
      ]
    },
    "/workspaces/CoffeeCraze/node_modules/@openzeppelin/contracts-upgradeable/token/ERC20/ERC20Upgradeable.sol": {
      "lastModificationDate": 1751804742181,
      "contentHash": "d98c902f3c91d73bb9f688ad15065ab8",
      "sourceName": "@openzeppelin/contracts-upgradeable/token/ERC20/ERC20Upgradeable.sol",
      "solcConfig": {
        "version": "0.8.24",
        "settings": {
          "evmVersion": "paris",
          "optimizer": {
            "enabled": false,
            "runs": 200
          },
          "outputSelection": {
            "*": {
              "*": [
                "abi",
                "evm.bytecode",
                "evm.deployedBytecode",
                "evm.methodIdentifiers",
                "metadata",
                "storageLayout"
              ],
              "": [
                "ast"
              ]
            }
          }
        }
      },
      "imports": [
        "@openzeppelin/contracts/token/ERC20/IERC20.sol",
        "@openzeppelin/contracts/token/ERC20/extensions/IERC20Metadata.sol",
        "../../utils/ContextUpgradeable.sol",
        "@openzeppelin/contracts/interfaces/draft-IERC6093.sol",
        "../../proxy/utils/Initializable.sol"
      ],
      "versionPragmas": [
        "^0.8.20"
      ],
      "artifacts": [
        "ERC20Upgradeable"
      ]
    },
    "/workspaces/CoffeeCraze/node_modules/@openzeppelin/contracts-upgradeable/utils/ContextUpgradeable.sol": {
      "lastModificationDate": 1751804742173,
      "contentHash": "c28aaa25d083a9a55bd9ec9e0b785122",
      "sourceName": "@openzeppelin/contracts-upgradeable/utils/ContextUpgradeable.sol",
      "solcConfig": {
        "version": "0.8.24",
        "settings": {
          "evmVersion": "paris",
          "optimizer": {
            "enabled": false,
            "runs": 200
          },
          "outputSelection": {
            "*": {
              "*": [
                "abi",
                "evm.bytecode",
                "evm.deployedBytecode",
                "evm.methodIdentifiers",
                "metadata",
                "storageLayout"
              ],
              "": [
                "ast"
              ]
            }
          }
        }
      },
      "imports": [
        "../proxy/utils/Initializable.sol"
      ],
      "versionPragmas": [
        "^0.8.20"
      ],
      "artifacts": [
        "ContextUpgradeable"
      ]
    },
    "/workspaces/CoffeeCraze/node_modules/@openzeppelin/contracts-upgradeable/proxy/utils/Initializable.sol": {
      "lastModificationDate": 1751804742199,
      "contentHash": "2acae54ad209714bca07edf4bae32f72",
      "sourceName": "@openzeppelin/contracts-upgradeable/proxy/utils/Initializable.sol",
      "solcConfig": {
        "version": "0.8.24",
        "settings": {
          "evmVersion": "paris",
          "optimizer": {
            "enabled": false,
            "runs": 200
          },
          "outputSelection": {
            "*": {
              "*": [
                "abi",
                "evm.bytecode",
                "evm.deployedBytecode",
                "evm.methodIdentifiers",
                "metadata",
                "storageLayout"
              ],
              "": [
                "ast"
              ]
            }
          }
        }
      },
      "imports": [],
      "versionPragmas": [
        "^0.8.20"
      ],
      "artifacts": [
        "Initializable"
      ]
    },
    "/workspaces/CoffeeCraze/node_modules/@openzeppelin/contracts/token/ERC20/IERC20.sol": {
      "lastModificationDate": 1751804741771,
      "contentHash": "8f19f64d2adadf448840908bbaf431c8",
      "sourceName": "@openzeppelin/contracts/token/ERC20/IERC20.sol",
      "solcConfig": {
        "version": "0.8.24",
        "settings": {
          "evmVersion": "paris",
          "optimizer": {
            "enabled": false,
            "runs": 200
          },
          "outputSelection": {
            "*": {
              "*": [
                "abi",
                "evm.bytecode",
                "evm.deployedBytecode",
                "evm.methodIdentifiers",
                "metadata",
                "storageLayout"
              ],
              "": [
                "ast"
              ]
            }
          }
        }
      },
      "imports": [],
      "versionPragmas": [
        "^0.8.20"
      ],
      "artifacts": [
        "IERC20"
      ]
    },
    "/workspaces/CoffeeCraze/node_modules/@openzeppelin/contracts/token/ERC20/extensions/IERC20Metadata.sol": {
      "lastModificationDate": 1751804741772,
      "contentHash": "794db3115001aa372c79326fcfd44b1f",
      "sourceName": "@openzeppelin/contracts/token/ERC20/extensions/IERC20Metadata.sol",
      "solcConfig": {
        "version": "0.8.24",
        "settings": {
          "evmVersion": "paris",
          "optimizer": {
            "enabled": false,
            "runs": 200
          },
          "outputSelection": {
            "*": {
              "*": [
                "abi",
                "evm.bytecode",
                "evm.deployedBytecode",
                "evm.methodIdentifiers",
                "metadata",
                "storageLayout"
              ],
              "": [
                "ast"
              ]
            }
          }
        }
      },
      "imports": [
        "../IERC20.sol"
      ],
      "versionPragmas": [
        "^0.8.20"
      ],
      "artifacts": [
        "IERC20Metadata"
      ]
    },
    "/workspaces/CoffeeCraze/node_modules/@openzeppelin/contracts-upgradeable/utils/introspection/ERC165Upgradeable.sol": {
      "lastModificationDate": 1751804742179,
      "contentHash": "61838d7249e45e3941fc2a45d1091448",
      "sourceName": "@openzeppelin/contracts-upgradeable/utils/introspection/ERC165Upgradeable.sol",
      "solcConfig": {
        "version": "0.8.24",
        "settings": {
          "evmVersion": "paris",
          "optimizer": {
            "enabled": false,
            "runs": 200
          },
          "outputSelection": {
            "*": {
              "*": [
                "abi",
                "evm.bytecode",
                "evm.deployedBytecode",
                "evm.methodIdentifiers",
                "metadata",
                "storageLayout"
              ],
              "": [
                "ast"
              ]
            }
          }
        }
      },
      "imports": [
        "@openzeppelin/contracts/utils/introspection/IERC165.sol",
        "../../proxy/utils/Initializable.sol"
      ],
      "versionPragmas": [
        "^0.8.20"
      ],
      "artifacts": [
        "ERC165Upgradeable"
      ]
    },
    "/workspaces/CoffeeCraze/node_modules/@openzeppelin/contracts/interfaces/IERC721.sol": {
      "lastModificationDate": 1751804741836,
      "contentHash": "d8d23fc2f55ed934d1a1b91c9afd8526",
      "sourceName": "@openzeppelin/contracts/interfaces/IERC721.sol",
      "solcConfig": {
        "version": "0.8.24",
        "settings": {
          "evmVersion": "paris",
          "optimizer": {
            "enabled": false,
            "runs": 200
          },
          "outputSelection": {
            "*": {
              "*": [
                "abi",
                "evm.bytecode",
                "evm.deployedBytecode",
                "evm.methodIdentifiers",
                "metadata",
                "storageLayout"
              ],
              "": [
                "ast"
              ]
            }
          }
        }
      },
      "imports": [
        "../token/ERC721/IERC721.sol"
      ],
      "versionPragmas": [
        "^0.8.20"
      ],
      "artifacts": []
    },
    "/workspaces/CoffeeCraze/node_modules/@openzeppelin/contracts/interfaces/IERC4906.sol": {
      "lastModificationDate": 1751804741825,
      "contentHash": "273c26c9c728a6052d1175ace81d10b4",
      "sourceName": "@openzeppelin/contracts/interfaces/IERC4906.sol",
      "solcConfig": {
        "version": "0.8.24",
        "settings": {
          "evmVersion": "paris",
          "optimizer": {
            "enabled": false,
            "runs": 200
          },
          "outputSelection": {
            "*": {
              "*": [
                "abi",
                "evm.bytecode",
                "evm.deployedBytecode",
                "evm.methodIdentifiers",
                "metadata",
                "storageLayout"
              ],
              "": [
                "ast"
              ]
            }
          }
        }
      },
      "imports": [
        "./IERC165.sol",
        "./IERC721.sol"
      ],
      "versionPragmas": [
        "^0.8.20"
      ],
      "artifacts": [
        "IERC4906"
      ]
    },
    "/workspaces/CoffeeCraze/node_modules/@openzeppelin/contracts/interfaces/IERC165.sol": {
      "lastModificationDate": 1751804741746,
      "contentHash": "f808b485ee0cdc6768ee8385ae5f9a2a",
      "sourceName": "@openzeppelin/contracts/interfaces/IERC165.sol",
      "solcConfig": {
        "version": "0.8.24",
        "settings": {
          "evmVersion": "paris",
          "optimizer": {
            "enabled": false,
            "runs": 200
          },
          "outputSelection": {
            "*": {
              "*": [
                "abi",
                "evm.bytecode",
                "evm.deployedBytecode",
                "evm.methodIdentifiers",
                "metadata",
                "storageLayout"
              ],
              "": [
                "ast"
              ]
            }
          }
        }
      },
      "imports": [
        "../utils/introspection/IERC165.sol"
      ],
      "versionPragmas": [
        "^0.8.20"
      ],
      "artifacts": []
    },
    "/workspaces/CoffeeCraze/node_modules/@openzeppelin/contracts/token/ERC721/extensions/ERC721URIStorage.sol": {
      "lastModificationDate": 1751804741714,
      "contentHash": "9aefce4573c7ae661acf9d5d78d5450b",
      "sourceName": "@openzeppelin/contracts/token/ERC721/extensions/ERC721URIStorage.sol",
      "solcConfig": {
        "version": "0.8.24",
        "settings": {
          "evmVersion": "paris",
          "optimizer": {
            "enabled": false,
            "runs": 200
          },
          "outputSelection": {
            "*": {
              "*": [
                "abi",
                "evm.bytecode",
                "evm.deployedBytecode",
                "evm.methodIdentifiers",
                "metadata",
                "storageLayout"
              ],
              "": [
                "ast"
              ]
            }
          }
        }
      },
      "imports": [
        "../ERC721.sol",
        "../../../utils/Strings.sol",
        "../../../interfaces/IERC4906.sol",
        "../../../interfaces/IERC165.sol"
      ],
      "versionPragmas": [
        "^0.8.20"
      ],
      "artifacts": [
        "ERC721URIStorage"
      ]
    },
    "/workspaces/CoffeeCraze/contracts/contracts/LearningModuleNFT.sol": {
      "lastModificationDate": 1751805580777,
      "contentHash": "fe22067f88733f2f5d1009a5fa495a86",
      "sourceName": "contracts/LearningModuleNFT.sol",
      "solcConfig": {
        "version": "0.8.24",
        "settings": {
          "evmVersion": "paris",
          "optimizer": {
            "enabled": false,
            "runs": 200
          },
          "outputSelection": {
            "*": {
              "*": [
                "abi",
                "evm.bytecode",
                "evm.deployedBytecode",
                "evm.methodIdentifiers",
                "metadata",
                "storageLayout"
              ],
              "": [
                "ast"
              ]
            }
          }
        }
      },
      "imports": [
        "@openzeppelin/contracts/token/ERC721/extensions/ERC721URIStorage.sol",
        "@openzeppelin/contracts/access/Ownable.sol"
      ],
      "versionPragmas": [
        "^0.8.24"
      ],
      "artifacts": [
        "LearningModuleNFT"
      ]
    },
    "/workspaces/CoffeeCraze/node_modules/@openzeppelin/contracts-upgradeable/access/AccessControlUpgradeable.sol": {
      "lastModificationDate": 1751804742171,
      "contentHash": "cdbbb56cde3edf99d1426db8d104bb84",
      "sourceName": "@openzeppelin/contracts-upgradeable/access/AccessControlUpgradeable.sol",
      "solcConfig": {
        "version": "0.8.24",
        "settings": {
          "evmVersion": "paris",
          "optimizer": {
            "enabled": false,
            "runs": 200
          },
          "outputSelection": {
            "*": {
              "*": [
                "abi",
                "evm.bytecode",
                "evm.deployedBytecode",
                "evm.methodIdentifiers",
                "metadata",
                "storageLayout"
              ],
              "": [
                "ast"
              ]
            }
          }
        }
      },
      "imports": [
        "@openzeppelin/contracts/access/IAccessControl.sol",
        "../utils/ContextUpgradeable.sol",
        "../utils/introspection/ERC165Upgradeable.sol",
        "../proxy/utils/Initializable.sol"
      ],
      "versionPragmas": [
        "^0.8.20"
      ],
      "artifacts": [
        "AccessControlUpgradeable"
      ]
    },
    "/workspaces/CoffeeCraze/node_modules/@openzeppelin/contracts/access/IAccessControl.sol": {
      "lastModificationDate": 1751804741733,
      "contentHash": "80621031deacf7066ec81277f9b1463a",
      "sourceName": "@openzeppelin/contracts/access/IAccessControl.sol",
      "solcConfig": {
        "version": "0.8.24",
        "settings": {
          "evmVersion": "paris",
          "optimizer": {
            "enabled": false,
            "runs": 200
          },
          "outputSelection": {
            "*": {
              "*": [
                "abi",
                "evm.bytecode",
                "evm.deployedBytecode",
                "evm.methodIdentifiers",
                "metadata",
                "storageLayout"
              ],
              "": [
                "ast"
              ]
            }
          }
        }
      },
      "imports": [],
      "versionPragmas": [
        "^0.8.20"
      ],
      "artifacts": [
        "IAccessControl"
      ]
    },
    "/workspaces/CoffeeCraze/contracts/contracts/KofiCoin.sol": {
      "lastModificationDate": 1751800182159,
      "contentHash": "6b77f782edf3b012f0da0b7f9e28d0d8",
      "sourceName": "contracts/KofiCoin.sol",
      "solcConfig": {
        "version": "0.8.24",
        "settings": {
          "evmVersion": "paris",
          "optimizer": {
            "enabled": false,
            "runs": 200
          },
          "outputSelection": {
            "*": {
              "*": [
                "abi",
                "evm.bytecode",
                "evm.deployedBytecode",
                "evm.methodIdentifiers",
                "metadata",
                "storageLayout"
              ],
              "": [
                "ast"
              ]
            }
          }
        }
      },
      "imports": [
        "@openzeppelin/contracts-upgradeable/token/ERC20/ERC20Upgradeable.sol",
        "@openzeppelin/contracts-upgradeable/access/AccessControlUpgradeable.sol",
        "@openzeppelin/contracts-upgradeable/proxy/utils/UUPSUpgradeable.sol"
      ],
      "versionPragmas": [
        "^0.8.24"
      ],
      "artifacts": [
        "KofiCoin"
      ]
    },
    "/workspaces/CoffeeCraze/node_modules/@openzeppelin/contracts-upgradeable/proxy/utils/UUPSUpgradeable.sol": {
      "lastModificationDate": 1751804742203,
      "contentHash": "08db0b4bea3d52072346c326c5b857b7",
      "sourceName": "@openzeppelin/contracts-upgradeable/proxy/utils/UUPSUpgradeable.sol",
      "solcConfig": {
        "version": "0.8.24",
        "settings": {
          "evmVersion": "paris",
          "optimizer": {
            "enabled": false,
            "runs": 200
          },
          "outputSelection": {
            "*": {
              "*": [
                "abi",
                "evm.bytecode",
                "evm.deployedBytecode",
                "evm.methodIdentifiers",
                "metadata",
                "storageLayout"
              ],
              "": [
                "ast"
              ]
            }
          }
        }
      },
      "imports": [
        "@openzeppelin/contracts/interfaces/draft-IERC1822.sol",
        "@openzeppelin/contracts/proxy/ERC1967/ERC1967Utils.sol",
        "./Initializable.sol"
      ],
      "versionPragmas": [
        "^0.8.22"
      ],
      "artifacts": [
        "UUPSUpgradeable"
      ]
    },
    "/workspaces/CoffeeCraze/node_modules/@openzeppelin/contracts/interfaces/draft-IERC1822.sol": {
      "lastModificationDate": 1751804741694,
      "contentHash": "64a2b7a96950f0641c477993f3029477",
      "sourceName": "@openzeppelin/contracts/interfaces/draft-IERC1822.sol",
      "solcConfig": {
        "version": "0.8.24",
        "settings": {
          "evmVersion": "paris",
          "optimizer": {
            "enabled": false,
            "runs": 200
          },
          "outputSelection": {
            "*": {
              "*": [
                "abi",
                "evm.bytecode",
                "evm.deployedBytecode",
                "evm.methodIdentifiers",
                "metadata",
                "storageLayout"
              ],
              "": [
                "ast"
              ]
            }
          }
        }
      },
      "imports": [],
      "versionPragmas": [
        "^0.8.20"
      ],
      "artifacts": [
        "IERC1822Proxiable"
      ]
    },
    "/workspaces/CoffeeCraze/node_modules/@openzeppelin/contracts/proxy/ERC1967/ERC1967Utils.sol": {
      "lastModificationDate": 1751804741704,
      "contentHash": "c023a5b23ee35b40b3085e550ff3367f",
      "sourceName": "@openzeppelin/contracts/proxy/ERC1967/ERC1967Utils.sol",
      "solcConfig": {
        "version": "0.8.24",
        "settings": {
          "evmVersion": "paris",
          "optimizer": {
            "enabled": false,
            "runs": 200
          },
          "outputSelection": {
            "*": {
              "*": [
                "abi",
                "evm.bytecode",
                "evm.deployedBytecode",
                "evm.methodIdentifiers",
                "metadata",
                "storageLayout"
              ],
              "": [
                "ast"
              ]
            }
          }
        }
      },
      "imports": [
        "../beacon/IBeacon.sol",
        "../../interfaces/IERC1967.sol",
        "../../utils/Address.sol",
        "../../utils/StorageSlot.sol"
      ],
      "versionPragmas": [
        "^0.8.22"
      ],
      "artifacts": [
        "ERC1967Utils"
      ]
    },
    "/workspaces/CoffeeCraze/node_modules/@openzeppelin/contracts/interfaces/IERC1967.sol": {
      "lastModificationDate": 1751804741770,
      "contentHash": "4e17c826a54a8ee1a185449d4695d07d",
      "sourceName": "@openzeppelin/contracts/interfaces/IERC1967.sol",
      "solcConfig": {
        "version": "0.8.24",
        "settings": {
          "evmVersion": "paris",
          "optimizer": {
            "enabled": false,
            "runs": 200
          },
          "outputSelection": {
            "*": {
              "*": [
                "abi",
                "evm.bytecode",
                "evm.deployedBytecode",
                "evm.methodIdentifiers",
                "metadata",
                "storageLayout"
              ],
              "": [
                "ast"
              ]
            }
          }
        }
      },
      "imports": [],
      "versionPragmas": [
        "^0.8.20"
      ],
      "artifacts": [
        "IERC1967"
      ]
    },
    "/workspaces/CoffeeCraze/node_modules/@openzeppelin/contracts/utils/Address.sol": {
      "lastModificationDate": 1751804741686,
      "contentHash": "5b9a49c25d7edbc48ffcbd2c7e8a40ef",
      "sourceName": "@openzeppelin/contracts/utils/Address.sol",
      "solcConfig": {
        "version": "0.8.24",
        "settings": {
          "evmVersion": "paris",
          "optimizer": {
            "enabled": false,
            "runs": 200
          },
          "outputSelection": {
            "*": {
              "*": [
                "abi",
                "evm.bytecode",
                "evm.deployedBytecode",
                "evm.methodIdentifiers",
                "metadata",
                "storageLayout"
              ],
              "": [
                "ast"
              ]
            }
          }
        }
      },
      "imports": [
        "./Errors.sol"
      ],
      "versionPragmas": [
        "^0.8.20"
      ],
      "artifacts": [
        "Address"
      ]
    },
    "/workspaces/CoffeeCraze/node_modules/@openzeppelin/contracts/utils/StorageSlot.sol": {
      "lastModificationDate": 1751804741894,
      "contentHash": "e656d64c4ce918f3d13030b91c935134",
      "sourceName": "@openzeppelin/contracts/utils/StorageSlot.sol",
      "solcConfig": {
        "version": "0.8.24",
        "settings": {
          "evmVersion": "paris",
          "optimizer": {
            "enabled": false,
            "runs": 200
          },
          "outputSelection": {
            "*": {
              "*": [
                "abi",
                "evm.bytecode",
                "evm.deployedBytecode",
                "evm.methodIdentifiers",
                "metadata",
                "storageLayout"
              ],
              "": [
                "ast"
              ]
            }
          }
        }
      },
      "imports": [],
      "versionPragmas": [
        "^0.8.20"
      ],
      "artifacts": [
        "StorageSlot"
      ]
    },
    "/workspaces/CoffeeCraze/node_modules/@openzeppelin/contracts/proxy/beacon/IBeacon.sol": {
      "lastModificationDate": 1751804741740,
      "contentHash": "0a5c323fd908535580597848b8e550fb",
      "sourceName": "@openzeppelin/contracts/proxy/beacon/IBeacon.sol",
      "solcConfig": {
        "version": "0.8.24",
        "settings": {
          "evmVersion": "paris",
          "optimizer": {
            "enabled": false,
            "runs": 200
          },
          "outputSelection": {
            "*": {
              "*": [
                "abi",
                "evm.bytecode",
                "evm.deployedBytecode",
                "evm.methodIdentifiers",
                "metadata",
                "storageLayout"
              ],
              "": [
                "ast"
              ]
            }
          }
        }
      },
      "imports": [],
      "versionPragmas": [
        "^0.8.20"
      ],
      "artifacts": [
        "IBeacon"
      ]
    },
    "/workspaces/CoffeeCraze/node_modules/@openzeppelin/contracts/utils/Errors.sol": {
      "lastModificationDate": 1751804741716,
      "contentHash": "6b5eac2b85500c3012977849cfd633d8",
      "sourceName": "@openzeppelin/contracts/utils/Errors.sol",
      "solcConfig": {
        "version": "0.8.24",
        "settings": {
          "evmVersion": "paris",
          "optimizer": {
            "enabled": false,
            "runs": 200
          },
          "outputSelection": {
            "*": {
              "*": [
                "abi",
                "evm.bytecode",
                "evm.deployedBytecode",
                "evm.methodIdentifiers",
                "metadata",
                "storageLayout"
              ],
              "": [
                "ast"
              ]
            }
          }
        }
      },
      "imports": [],
      "versionPragmas": [
        "^0.8.20"
      ],
      "artifacts": [
        "Errors"
      ]
    },
    "/workspaces/CoffeeCraze/contracts/contracts/Marketplace.sol": {
      "lastModificationDate": 1751808899390,
      "contentHash": "c2d933e67e31f44a0fa487397f8bfe6c",
      "sourceName": "contracts/Marketplace.sol",
      "solcConfig": {
        "version": "0.8.24",
        "settings": {
          "evmVersion": "paris",
          "optimizer": {
            "enabled": false,
            "runs": 200
          },
          "outputSelection": {
            "*": {
              "*": [
                "abi",
                "evm.bytecode",
                "evm.deployedBytecode",
                "evm.methodIdentifiers",
                "metadata",
                "storageLayout"
              ],
              "": [
                "ast"
              ]
            }
          }
        }
      },
      "imports": [
        "@openzeppelin/contracts/access/Ownable.sol"
      ],
      "versionPragmas": [
        "^0.8.24"
      ],
      "artifacts": [
        "Marketplace"
      ]
    }
  }
}
